{
  "steps": [
    {
      "name": "intro",
      "title": "Uniform Residential Loan Application",
      "subtitle": "",
      "elements": [
        {
          "name": "intro",
          "type": "label",
          "values": [
            "<p>This application is designed to be completed by the applicant(s) with the Lender’s assistance. Applicants should complete this form as “Borrower” or “Co-Borrower,” as applicable. Co-Borrower information must also be provided (and the appropriate box checked) when  the income or assets of a person other than the Borrower (including the Borrower’s spouse) will be used as a basis for loan qualification or  the income or assets of the Borrower’s spouse or other person who has community property rights pursuant to state law will not be used as a basis for loan qualification, but his or her liabilities must be considered because the spouse or other person has community property rights pursuant to applicable law and Borrower resides in a community property state, the security property is located in a community property state, or the Borrower is relying on other property located in a community property state as a basis for repayment of the loan.</p>&nbsp;<p>If this is an application for joint credit, Borrower and Co-Borrower each agree that we intend to apply for joint credit (sign below):</p>"
          ]
        }
      ]
    },
    {
      "name": "mortgage-type",
      "title": "I. TYPE OF MORTGAGE AND TERMS OF LOAN",
      "subtitle": "Mortgage Applied for",
      "elements": [
        {
          "name": "mortgage-type",
          "type": "radio",
          "values": [
            "VA",
            "Conventional",
            "FHA",
            "USDA / Rural Housing Service",
            "Other (explain)"
          ],
          "validation": {
            "required": "true"
          }
        }
      ]
    },
    {
      "name": "agency-case-number",
      "title": "I. TYPE OF MORTGAGE AND TERMS OF LOAN",
      "subtitle": "Agency Case Number",
      "elements": [
        {
          "name": "agency-case-number",
          "type": "text",
          "placeholder": "Agency Case Number"
        }
      ]
    },
    {
      "name": "lender-case-number",
      "title": "I. TYPE OF MORTGAGE AND TERMS OF LOAN",
      "subtitle": "Lender Case Number",
      "elements": [
        {
          "name": "lender-case-number",
          "type": "text",
          "placeholder": "Lender Case Number"
        }
      ]
    },
    {
      "name": "amount",
      "title": "I. TYPE OF MORTGAGE AND TERMS OF LOAN",
      "subtitle": "Amount",
      "elements": [
        {
          "name": "amount",
          "type": "number",
          "placeholder": "$"
        }
      ]
    },
    {
      "name": "interest-rate",
      "title": "I. TYPE OF MORTGAGE AND TERMS OF LOAN",
      "subtitle": "Interest Rate",
      "elements": [
        {
          "name": "interest-rate",
          "type": "number",
          "placeholder": "%"
        }
      ]
    },
    {
      "name": "number-of-months",
      "title": "I. TYPE OF MORTGAGE AND TERMS OF LOAN",
      "subtitle": "Number of Months",
      "elements": [
        {
          "name": "number-of-months",
          "type": "number",
          "placeholder": ""
        }
      ]
    },
    {
      "name": "amortization-type",
      "title": "I. TYPE OF MORTGAGE AND TERMS OF LOAN",
      "subtitle": "Amortization Type",
      "elements": [
        {
          "name": "amortization-type",
          "type": "radio",
          "values": [
            "Fixed Rate",
            "GPM",
            "ARM (type)",
            "Other (explain)"
          ]
        }
      ]
    },
    {
      "name": "property-address-street",
      "title": "II. PROPERTY INFORMATION AND PURPOSE OF LOAN",
      "subtitle": "Subject Property Address",
      "elements": [
        {
          "name": "property-address-street",
          "type": "text",
          "placeholder": "Street"
        },
        {
          "name": "property-address-city",
          "type": "text",
          "placeholder": "City"
        },
        {
          "name": "property-address-state",
          "type": "text",
          "placeholder": "State"
        },
        {
          "name": "property-address-zip",
          "type": "number",
          "placeholder": "Zip"
        }
      ]
    },
    {
      "name": "number-of-units",
      "title": "II. PROPERTY INFORMATION AND PURPOSE OF LOAN",
      "subtitle": "Subject Property Address",
      "elements": [
        {
          "name": "number-of-units",
          "type": "number",
          "placeholder": "Number of units"
        },
        {
          "name": "year-built",
          "type": "number",
          "placeholder": "Year built"
        }
      ]
    },
    {
      "name": "legal-description",
      "title": "II. PROPERTY INFORMATION AND PURPOSE OF LOAN",
      "subtitle": "Legal Description of Subject Property",
      "elements": [
        {
          "name": "legal-description",
          "type": "textarea",
          "placeholder": "Legal Description of Subject Property"
        }
      ]
    },
    {
      "name": "purpose-of-loan",
      "title": "II. PROPERTY INFORMATION AND PURPOSE OF LOAN",
      "subtitle": "Purpose of Loan",
      "elements": [
        {
          "name": "purpose-of-loan",
          "type": "radio",
          "values": [
            "Purchase",
            "Refinance",
            "Construction",
            "Construction-Permanent",
            "Other (explain)"
          ]
        }
      ]
    },
    {
      "name": "property-will-be",
      "title": "II. PROPERTY INFORMATION AND PURPOSE OF LOAN",
      "subtitle": "Property will be",
      "elements": [
        {
          "name": "property-will-be",
          "type": "radio",
          "values": [
            "Primary Residence",
            "Secondary Residence",
            "Investment"
          ]
        }
      ]
    },
    {
      "name": "construction-loan",
      "title": "II. PROPERTY INFORMATION AND PURPOSE OF LOAN",
      "subtitle": "",
      "elements": [
        {
          "name": "construction-loan",
          "type": "checkbox",
          "isConditional": true,
          "values": [
            "Check this box, if this application is for a construction or construction-permanent loan."
          ]
        }
      ],
      "conditional-elements": [
        {
          "name": "year-acquired",
          "type": "number",
          "placeholder": "Year Lot acquired"
        },
        {
          "name": "original-cost",
          "type": "number",
          "placeholder": "Original Cost"
        }
      ]
    }
  ]
}
